tapostreamer/__init__.py
tapostreamer/main.py
tapostreamer-0.3.9.dist-info/METADATA
tapostreamer-0.3.9.dist-info/WHEEL
tapostreamer-0.3.9.dist-info/entry_points.txt
tapostreamer-0.3.9.dist-info/licenses/LICENSE
tapostreamer-0.3.9.dist-info/RECORD
