Metadata-Version: 2.4
Name: tapostreamer
Version: 0.3.9
Summary: TapoStreamer is an Python application that shows the video streaming from the cameras made by TP-Link.
Project-URL: Homepage, https://github.com/rioriost/homebrew-tapostreamer
Project-URL: Issues, https://github.com/rioriost/homebrew-tapostreamer/issues
Author-email: Rio Fujita <rifujita@microsoft.com>
License: MIT License
License-File: LICENSE
Requires-Python: >=3.11
Requires-Dist: keyring>=25.6.0
Requires-Dist: opencv-python>=4.13.0.90
